qbizinc/airflow/__init__.py
qbizinc/airflow/presto_ecs_operator.py
qbizinc/airflow/presto_kubernetes_operator.py
qbiz_airflow_presto-0.1rc1.dist-info/LICENSE
qbiz_airflow_presto-0.1rc1.dist-info/METADATA
qbiz_airflow_presto-0.1rc1.dist-info/WHEEL
qbiz_airflow_presto-0.1rc1.dist-info/top_level.txt
qbiz_airflow_presto-0.1rc1.dist-info/RECORD
