Metadata-Version: 2.1
Name: qbiz-airflow-presto
Version: 0.1rc1
Summary: A containerized Presto cluster for AWS.
Home-page: https://github.com/QBizinc/airflow-presto
Author: Soren Archibald, Cameron Cole and Paco Valdez
Author-email: soren@qbizinc.com
License: UNKNOWN
Platform: UNKNOWN
Classifier: Programming Language :: Python :: 3
Classifier: License :: OSI Approved :: MIT License
Classifier: Operating System :: OS Independent
Requires-Python: >=3.7
Requires-Dist: boto3 (>=1.7.84)
Requires-Dist: botocore (>=1.10.84)
Requires-Dist: apache-airflow (>=1.10.12)
Requires-Dist: PyHive (>=0.6.2)
